<?xml version="1.0" encoding="UTF-8" ?>
<Value xmlns="http://opcfoundation.org/UA/2011/03/UANodeSet.xsd" xmlns:uax="http://opcfoundation.org/UA/2008/02/Types.xsd">
	<uax:ListOfString>
		<uax:String>&quot;0&quot;:{&quot;1 Name&quot;:&quot;Main Site&quot;,&quot;2 Latitude&quot;:&quot;25.997253696071304&quot;,&quot;3 Longitude&quot;:&quot;-97.15722430289206&quot;,&quot;4 Address&quot;:&quot;AGENT.OBJECTS.Test_01&quot;,&quot;5 Display&quot;:&quot;AGENT.DISPLAYS.MAIN.Water.Water_WA01_WA10&quot;}</uax:String>
		<uax:String>&quot;1&quot;:{&quot;1 Name&quot;:&quot;Main Site 45&quot;,&quot;2 Latitude&quot;:&quot;26.002441678120917&quot;,&quot;3 Longitude&quot;:&quot;-97.17692189150026&quot;,&quot;4 Address&quot;:&quot;AGENT.OBJECTS.Test_01&quot;,&quot;5 Display&quot;:&quot;AGENT.DISPLAYS.MAIN.Energy.Energy_EN01_EN10&quot;}</uax:String>
		<uax:String>&quot;2&quot;:{&quot;1 Name&quot;:&quot;Main Site 8&quot;,&quot;2 Latitude&quot;:&quot;25.995&quot;,&quot;3 Longitude&quot;:&quot;-97.155&quot;,&quot;4 Address&quot;:&quot;AGENT.OBJECTS.Test_01&quot;,&quot;5 Display&quot;:&quot;AGENT.DISPLAYS.Main&quot;}</uax:String>
		<uax:String>&quot;3&quot;:{&quot;1 Name&quot;:&quot;Test &quot;,&quot;2 Latitude&quot;:&quot;26.026088569484738&quot;,&quot;3 Longitude&quot;:&quot;-97.21742338390789&quot;,&quot;4 Address&quot;:&quot;AGENT.OBJECTS.Test_01&quot;,&quot;5 Display&quot;:&quot;AGENT.DISPLAYS.MAIN.Test2&quot;}</uax:String>
	</uax:ListOfString>
</Value>